{
  "Twister": [
    {
      "gift_num": 70527,
      "customEmojiId": "5431855576021753431",
      "gift_id": 7432871,
      "name": "Spy Agaric",
      "model": "Twister (1.5%)",
      "asset": "TON",
      "symbol": "Bloody Axe (1.8%)",
      "backdrop": "Ivory White (2%)",
      "availabilityIssued": 0,
      "availabilityTotal": 0,
      "backdropData": {},
      "message_in_channel": 0,
      "price": 4.5,
      "status": "forsale",
      "limited": false,
      "auction": null,
      "export_at": "2025-08-10T14:51:49.000Z",
      "premarketData": {}
    },
    {
      "gift_num": 81648,
      "customEmojiId": "5431855576021753431",
      "gift_id": 7112984,
      "name": "Spy Agaric",
      "model": "Twister (1.5%)",
      "asset": "TON",
      "symbol": "Autumn Leaves (1.2%)",
      "backdrop": "Desert Sand (2%)",
      "availabilityIssued": 0,
      "availabilityTotal": 0,
      "backdropData": {},
      "message_in_channel": 0,
      "price": 3.5,
      "status": "forsale",
      "limited": false,
      "auction": null,
      "export_at": "2025-07-23T20:24:37.000Z",
      "premarketData": {}
    },
    {
      "gift_num": 43888,
      "customEmojiId": "5431855576021753431",
      "gift_id": 5961891,
      "name": "Spy Agaric",
      "model": "Twister (1.5%)",
      "asset": "TON",
      "symbol": "Voodoo Doll (1.5%)",
      "backdrop": "Hunter Green (2%)",
      "availabilityIssued": 0,
      "availabilityTotal": 0,
      "backdropData": {},
      "message_in_channel": 0,
      "price": 4,
      "status": "forsale",
      "limited": false,
      "auction": null,
      "export_at": "2025-06-23T12:43:09.000Z",
      "premarketData": {}
    },
    {
      "gift_num": 10272,
      "customEmojiId": "5431855576021753431",
      "gift_id": 5962964,
      "name": "Spy Agaric",
      "model": "Twister (1.5%)",
      "asset": "TON",
      "symbol": "Spanner (0.5%)",
      "backdrop": "Strawberry (1.5%)",
      "availabilityIssued": 0,
      "availabilityTotal": 0,
      "backdropData": {},
      "message_in_channel": 0,
      "price": 3.8,
      "status": "forsale",
      "limited": false,
      "auction": null,
      "export_at": "2025-06-23T12:48:27.000Z",
      "premarketData": {}
    },
    {
      "gift_num": 70840,
      "customEmojiId": "5431855576021753431",
      "gift_id": 7234745,
      "name": "Spy Agaric",
      "model": "Twister (1.5%)",
      "asset": "TON",
      "symbol": "Spooky Cat (1.8%)",
      "backdrop": "Ivory White (2%)",
      "availabilityIssued": 0,
      "availabilityTotal": 0,
      "backdropData": {},
      "message_in_channel": 0,
      "price": 15,
      "status": "forsale",
      "limited": false,
      "auction": null,
      "export_at": "2025-07-29T16:30:25.000Z",
      "premarketData": {}
    },
    {
      "gift_num": 28730,
      "customEmojiId": "5431855576021753431",
      "gift_id": 7183802,
      "name": "Spy Agaric",
      "model": "Twister (1.5%)",
      "asset": "TON",
      "symbol": "Ghost (1.5%)",
      "backdrop": "Turquoise (1.5%)",
      "availabilityIssued": 0,
      "availabilityTotal": 0,
      "backdropData": {},
      "message_in_channel": 0,
      "price": 7.5,
      "status": "forsale",
      "limited": false,
      "auction": null,
      "export_at": "2025-07-26T20:17:29.000Z",
      "premarketData": {}
    },
    {
      "gift_num": 28729,
      "customEmojiId": "5431855576021753431",
      "gift_id": 7183700,
      "name": "Spy Agaric",
      "model": "Twister (1.5%)",
      "asset": "TON",
      "symbol": "Crusader (0.5%)",
      "backdrop": "Aquamarine (2%)",
      "availabilityIssued": 0,
      "availabilityTotal": 0,
      "backdropData": {},
      "message_in_channel": 0,
      "price": 7.5,
      "status": "forsale",
      "limited": false,
      "auction": null,
      "export_at": "2025-07-26T20:12:11.000Z",
      "premarketData": {}
    },
    {
      "gift_num": 45362,
      "customEmojiId": "5431855576021753431",
      "gift_id": 7142197,
      "name": "Spy Agaric",
      "model": "Twister (1.5%)",
      "asset": "TON",
      "symbol": "Fish Skeleton (1.2%)",
      "backdrop": "Khaki Green (2%)",
      "availabilityIssued": 0,
      "availabilityTotal": 0,
      "backdropData": {},
      "message_in_channel": 0,
      "price": 3.1,
      "status": "forsale",
      "limited": false,
      "auction": null,
      "export_at": "2025-07-24T20:39:29.000Z",
      "premarketData": {}
    },
    {
      "gift_num": 80501,
      "customEmojiId": "5431855576021753431",
      "gift_id": 6045968,
      "name": "Spy Agaric",
      "model": "Twister (1.5%)",
      "asset": "TON",
      "symbol": "Poison Drop (1.5%)",
      "backdrop": "Hunter Green (2%)",
      "availabilityIssued": 0,
      "availabilityTotal": 0,
      "backdropData": {},
      "message_in_channel": 0,
      "price": 5,
      "status": "forsale",
      "limited": false,
      "auction": null,
      "export_at": "2025-06-23T20:18:47.000Z",
      "premarketData": {}
    },
    {
      "gift_num": 80493,
      "customEmojiId": "5431855576021753431",
      "gift_id": 6045745,
      "name": "Spy Agaric",
      "model": "Twister (1.5%)",
      "asset": "TON",
      "symbol": "Coffin (1.8%)",
      "backdrop": "Mint Green (1.5%)",
      "availabilityIssued": 0,
      "availabilityTotal": 0,
      "backdropData": {},
      "message_in_channel": 0,
      "price": 5,
      "status": "forsale",
      "limited": false,
      "auction": null,
      "export_at": "2025-06-23T20:17:38.000Z",
      "premarketData": {}
    },
    {
      "gift_num": 74796,
      "customEmojiId": "5431855576021753431",
      "gift_id": 7103307,
      "name": "Spy Agaric",
      "model": "Twister (1.5%)",
      "asset": "TON",
      "symbol": "Poison Drop (1.5%)",
      "backdrop": "Steel Grey (2%)",
      "availabilityIssued": 0,
      "availabilityTotal": 0,
      "backdropData": {},
      "message_in_channel": 0,
      "price": 4.89,
      "status": "forsale",
      "limited": false,
      "auction": null,
      "export_at": "2025-07-23T12:46:14.000Z",
      "premarketData": {}
    },
    {
      "gift_num": 59397,
      "customEmojiId": "5431855576021753431",
      "gift_id": 7017488,
      "name": "Spy Agaric",
      "model": "Twister (1.5%)",
      "asset": "TON",
      "symbol": "Birthday Cake (0.5%)",
      "backdrop": "Onyx Black (1%)",
      "availabilityIssued": 0,
      "availabilityTotal": 0,
      "backdropData": {},
      "message_in_channel": 0,
      "price": 20,
      "status": "forsale",
      "limited": false,
      "auction": null,
      "export_at": "2025-07-19T21:36:19.000Z",
      "premarketData": {}
    },
    {
      "gift_num": 74578,
      "customEmojiId": "5431855576021753431",
      "gift_id": 6966000,
      "name": "Spy Agaric",
      "model": "Twister (1.5%)",
      "asset": "TON",
      "symbol": "Voodoo Doll (1.5%)",
      "backdrop": "Pure Gold (1.5%)",
      "availabilityIssued": 0,
      "availabilityTotal": 0,
      "backdropData": {},
      "message_in_channel": 0,
      "price": 10,
      "status": "forsale",
      "limited": false,
      "auction": null,
      "export_at": "2025-07-17T16:45:36.000Z",
      "premarketData": {}
    },
    {
      "gift_num": 28760,
      "customEmojiId": "5431855576021753431",
      "gift_id": 6037964,
      "name": "Spy Agaric",
      "model": "Twister (1.5%)",
      "asset": "TON",
      "symbol": "Blood Drop (1.8%)",
      "backdrop": "Azure Blue (2%)",
      "availabilityIssued": 0,
      "availabilityTotal": 0,
      "backdropData": {},
      "message_in_channel": 0,
      "price": 8,
      "status": "forsale",
      "limited": false,
      "auction": null,
      "export_at": "2025-06-23T19:34:38.000Z",
      "premarketData": {}
    },
    {
      "gift_num": 59163,
      "customEmojiId": "5431855576021753431",
      "gift_id": 6754746,
      "name": "Spy Agaric",
      "model": "Twister (1.5%)",
      "asset": "TON",
      "symbol": "Skull (1.8%)",
      "backdrop": "Hunter Green (2%)",
      "availabilityIssued": 0,
      "availabilityTotal": 0,
      "backdropData": {},
      "message_in_channel": 0,
      "price": 4,
      "status": "forsale",
      "limited": false,
      "auction": null,
      "export_at": "2025-07-09T15:25:24.000Z",
      "premarketData": {}
    },
    {
      "gift_num": 2149,
      "customEmojiId": "5431855576021753431",
      "gift_id": 6138218,
      "name": "Spy Agaric",
      "model": "Twister (1.5%)",
      "asset": "TON",
      "symbol": "Cauldron (1.8%)",
      "backdrop": "Amber (1.5%)",
      "availabilityIssued": 0,
      "availabilityTotal": 0,
      "backdropData": {},
      "message_in_channel": 0,
      "price": 5,
      "status": "forsale",
      "limited": false,
      "auction": null,
      "export_at": "2025-06-24T14:00:57.000Z",
      "premarketData": {}
    },
    {
      "gift_num": 76295,
      "customEmojiId": "5431855576021753431",
      "gift_id": 6602899,
      "name": "Spy Agaric",
      "model": "Twister (1.5%)",
      "asset": "TON",
      "symbol": "Candle (1.8%)",
      "backdrop": "Steel Grey (2%)",
      "availabilityIssued": 0,
      "availabilityTotal": 0,
      "backdropData": {},
      "message_in_channel": 0,
      "price": 8.08,
      "status": "forsale",
      "limited": false,
      "auction": null,
      "export_at": "2025-07-03T14:31:31.000Z",
      "premarketData": {}
    },
    {
      "gift_num": 75112,
      "customEmojiId": "5431855576021753431",
      "gift_id": 6600669,
      "name": "Spy Agaric",
      "model": "Twister (1.5%)",
      "asset": "TON",
      "symbol": "Lollipop (1.5%)",
      "backdrop": "Electric Indigo (1.5%)",
      "availabilityIssued": 0,
      "availabilityTotal": 0,
      "backdropData": {},
      "message_in_channel": 0,
      "price": 4.85,
      "status": "forsale",
      "limited": false,
      "auction": null,
      "export_at": "2025-07-03T13:20:32.000Z",
      "premarketData": {}
    },
    {
      "gift_num": 75081,
      "customEmojiId": "5431855576021753431",
      "gift_id": 6600581,
      "name": "Spy Agaric",
      "model": "Twister (1.5%)",
      "asset": "TON",
      "symbol": "Candle (1.8%)",
      "backdrop": "Sapphire (2%)",
      "availabilityIssued": 0,
      "availabilityTotal": 0,
      "backdropData": {},
      "message_in_channel": 0,
      "price": 4.85,
      "status": "forsale",
      "limited": false,
      "auction": null,
      "export_at": "2025-07-03T13:18:21.000Z",
      "premarketData": {}
    },
    {
      "gift_num": 42107,
      "customEmojiId": "5431855576021753431",
      "gift_id": 6600779,
      "name": "Spy Agaric",
      "model": "Twister (1.5%)",
      "asset": "TON",
      "symbol": "Oxen of Fire (0.4%)",
      "backdrop": "Sky Blue (1.5%)",
      "availabilityIssued": 0,
      "availabilityTotal": 0,
      "backdropData": {},
      "message_in_channel": 0,
      "price": 4.85,
      "status": "forsale",
      "limited": false,
      "auction": null,
      "export_at": "2025-07-03T13:23:54.000Z",
      "premarketData": {}
    },
    {
      "gift_num": 42821,
      "customEmojiId": "5431855576021753431",
      "gift_id": 6600084,
      "name": "Spy Agaric",
      "model": "Twister (1.5%)",
      "asset": "TON",
      "symbol": "Mafdet (0.4%)",
      "backdrop": "Moonstone (2%)",
      "availabilityIssued": 0,
      "availabilityTotal": 0,
      "backdropData": {},
      "message_in_channel": 0,
      "price": 4.85,
      "status": "forsale",
      "limited": false,
      "auction": null,
      "export_at": "2025-07-03T13:05:43.000Z",
      "premarketData": {}
    },
    {
      "gift_num": 42630,
      "customEmojiId": "5431855576021753431",
      "gift_id": 6599940,
      "name": "Spy Agaric",
      "model": "Twister (1.5%)",
      "asset": "TON",
      "symbol": "Lollipop (1.5%)",
      "backdrop": "Indigo Dye (1.5%)",
      "availabilityIssued": 0,
      "availabilityTotal": 0,
      "backdropData": {},
      "message_in_channel": 0,
      "price": 4.85,
      "status": "forsale",
      "limited": false,
      "auction": null,
      "export_at": "2025-07-03T13:02:38.000Z",
      "premarketData": {}
    },
    {
      "gift_num": 75196,
      "customEmojiId": "5431855576021753431",
      "gift_id": 6586819,
      "name": "Spy Agaric",
      "model": "Twister (1.5%)",
      "asset": "TON",
      "symbol": "Sauron (1.8%)",
      "backdrop": "Chocolate (2%)",
      "availabilityIssued": 0,
      "availabilityTotal": 0,
      "backdropData": {},
      "message_in_channel": 0,
      "price": 4.85,
      "status": "forsale",
      "limited": false,
      "auction": null,
      "export_at": "2025-07-02T23:14:54.000Z",
      "premarketData": {}
    },
    {
      "gift_num": 76442,
      "customEmojiId": "5431855576021753431",
      "gift_id": 6572200,
      "name": "Spy Agaric",
      "model": "Twister (1.5%)",
      "asset": "TON",
      "symbol": "Octopus (0.4%)",
      "backdrop": "English Violet (2%)",
      "availabilityIssued": 0,
      "availabilityTotal": 0,
      "backdropData": {},
      "message_in_channel": 0,
      "price": 4.85,
      "status": "forsale",
      "limited": false,
      "auction": null,
      "export_at": "2025-07-02T15:14:43.000Z",
      "premarketData": {}
    },
    {
      "gift_num": 74820,
      "customEmojiId": "5431855576021753431",
      "gift_id": 6571640,
      "name": "Spy Agaric",
      "model": "Twister (1.5%)",
      "asset": "TON",
      "symbol": "Human Scull (1.8%)",
      "backdrop": "Strawberry (1.5%)",
      "availabilityIssued": 0,
      "availabilityTotal": 0,
      "backdropData": {},
      "message_in_channel": 0,
      "price": 4.85,
      "status": "forsale",
      "limited": false,
      "auction": null,
      "export_at": "2025-07-02T15:05:35.000Z",
      "premarketData": {}
    },
    {
      "gift_num": 73894,
      "customEmojiId": "5431855576021753431",
      "gift_id": 6571905,
      "name": "Spy Agaric",
      "model": "Twister (1.5%)",
      "asset": "TON",
      "symbol": "Gravestone (1.8%)",
      "backdrop": "Cobalt Blue (2%)",
      "availabilityIssued": 0,
      "availabilityTotal": 0,
      "backdropData": {},
      "message_in_channel": 0,
      "price": 4.85,
      "status": "forsale",
      "limited": false,
      "auction": null,
      "export_at": "2025-07-02T15:09:42.000Z",
      "premarketData": {}
    },
    {
      "gift_num": 43062,
      "customEmojiId": "5431855576021753431",
      "gift_id": 6571679,
      "name": "Spy Agaric",
      "model": "Twister (1.5%)",
      "asset": "TON",
      "symbol": "Strawberry (0.5%)",
      "backdrop": "Mystic Pearl (2%)",
      "availabilityIssued": 0,
      "availabilityTotal": 0,
      "backdropData": {},
      "message_in_channel": 0,
      "price": 4.85,
      "status": "forsale",
      "limited": false,
      "auction": null,
      "export_at": "2025-07-02T15:06:17.000Z",
      "premarketData": {}
    },
    {
      "gift_num": 11070,
      "customEmojiId": "5431855576021753431",
      "gift_id": 4994900,
      "name": "Spy Agaric",
      "model": "Twister (1.5%)",
      "asset": "TON",
      "symbol": "Fehu Rune (0.5%)",
      "backdrop": "Dark Lilac (1.5%)",
      "availabilityIssued": 0,
      "availabilityTotal": 0,
      "backdropData": {},
      "message_in_channel": 0,
      "price": 8,
      "status": "forsale",
      "limited": false,
      "auction": null,
      "export_at": "2025-05-31T13:48:16.000Z",
      "premarketData": {}
    },
    {
      "gift_num": 29092,
      "customEmojiId": "5431855576021753431",
      "gift_id": 6072620,
      "name": "Spy Agaric",
      "model": "Twister (1.5%)",
      "asset": "TON",
      "symbol": "Bee (0.5%)",
      "backdrop": "Moonstone (2%)",
      "availabilityIssued": 0,
      "availabilityTotal": 0,
      "backdropData": {},
      "message_in_channel": 0,
      "price": 9,
      "status": "forsale",
      "limited": false,
      "auction": null,
      "export_at": "2025-06-24T00:07:32.000Z",
      "premarketData": {}
    },
    {
      "gift_num": 43351,
      "customEmojiId": "5431855576021753431",
      "gift_id": 6466233,
      "name": "Spy Agaric",
      "model": "Twister (1.5%)",
      "asset": "TON",
      "symbol": "Fish Skeleton (1.2%)",
      "backdrop": "Cyberpunk (2%)",
      "availabilityIssued": 0,
      "availabilityTotal": 0,
      "backdropData": {},
      "message_in_channel": 0,
      "price": 10,
      "status": "forsale",
      "limited": false,
      "auction": null,
      "export_at": "2025-06-29T22:34:44.000Z",
      "premarketData": {}
    }
  ]
}